vaulti_ansible/__about__.py
vaulti_ansible/__init__.py
vaulti_ansible/__main__.py
vaulti_ansible/vaulti.py
vaulti_ansible-0.1.11.dist-info/METADATA
vaulti_ansible-0.1.11.dist-info/WHEEL
vaulti_ansible-0.1.11.dist-info/entry_points.txt
vaulti_ansible-0.1.11.dist-info/licenses/LICENSE
vaulti_ansible-0.1.11.dist-info/RECORD
