Metadata-Version: 2.4
Name: vaulti_ansible
Version: 0.1.11
Summary: Utility for Ansible Vault inline-encrypted variables
Project-URL: Homepage, https://github.com/oveee92/vaulti
Project-URL: Repository, https://github.com/oveee92/vaulti
Project-URL: Issues, https://github.com/oveee92/vaulti/issues
Author-email: Ove <oveee92@gmail.com>
License: MIT
License-File: LICENSE
Keywords: ansible,ansible-vault
Classifier: Development Status :: 4 - Beta
Classifier: Framework :: Ansible
Classifier: Intended Audience :: System Administrators
Classifier: License :: OSI Approved :: MIT License
Classifier: Operating System :: POSIX :: Linux
Classifier: Programming Language :: Python :: 3
Classifier: Topic :: Security :: Cryptography
Classifier: Topic :: System :: Systems Administration
Classifier: Topic :: Utilities
Requires-Python: >=3.8
Requires-Dist: ruamel-yaml>=0.16.6
